LICENSE
README.md
pyproject.toml
setup.py
RFMCustomer/RFMCustomer.py
RFMCustomer/__init__.py
RFMCustomer.egg-info/PKG-INFO
RFMCustomer.egg-info/SOURCES.txt
RFMCustomer.egg-info/dependency_links.txt
RFMCustomer.egg-info/requires.txt
RFMCustomer.egg-info/top_level.txt