Metadata-Version: 2.1
Name: RFMCustomer
Version: 0.0.3
Summary: Librería para realizar una segmentación RFM.
Home-page: https://github.com/SebastianUrdaneguiBisalaya/Segmentacion-RFM
Author: Sebastian Marat Urdanegui Bisalaya
Author-email: sebasurdanegui@gmail.com
License: MIT
License-File: LICENSE
